{
	"miniprogramRoot": "miniprogram/",
	"cloudfunctionRoot": "cloudfunctions/",
	"setting": {
		"urlCheck": false,
		"es6": true,
		"postcss": true,
		"minified": true,
		"newFeature": true
	},
	"appid": "wx106a407772059263",
	"projectname": "wechat_crm",
	"libVersion": "2.0.4",
	"condition": {
		"search": {
			"current": -1,
			"list": []
		},
		"conversation": {
			"current": -1,
			"list": []
		},
		"plugin": {
			"current": -1,
			"list": []
		},
		"game": {
			"list": []
		},
		"miniprogram": {
			"current": 0,
			"list": [
				{
					"id": -1,
					"name": "home",
					"pathName": "pages/tabBar/home/home"
				}
			]
		}
	}
}